django_report_utils-0.3.15.dist-info/DESCRIPTION.rst
django_report_utils-0.3.15.dist-info/METADATA
django_report_utils-0.3.15.dist-info/RECORD
django_report_utils-0.3.15.dist-info/WHEEL
django_report_utils-0.3.15.dist-info/metadata.json
django_report_utils-0.3.15.dist-info/pbr.json
django_report_utils-0.3.15.dist-info/top_level.txt
report_utils/__init__.py
report_utils/mixins.py
report_utils/model_introspection.py
report_utils/utils.py
